veranda/__init__.py
veranda/utils.py
veranda/raster/__init__.py
veranda/raster/gdalport.py
veranda/raster/mosaic/__init__.py
veranda/raster/mosaic/base.py
veranda/raster/mosaic/geotiff.py
veranda/raster/mosaic/netcdf.py
veranda/raster/native/__init__.py
veranda/raster/native/geotiff.py
veranda/raster/native/netcdf.py
veranda/vector/__init__.py
veranda/vector/native/__init__.py
veranda/vector/native/shp.py
veranda-1.3.0.dist-info/licenses/LICENSE.txt
veranda-1.3.0.dist-info/METADATA
veranda-1.3.0.dist-info/WHEEL
veranda-1.3.0.dist-info/top_level.txt
veranda-1.3.0.dist-info/RECORD
